tronpyapi/__init__.py
tronpyapi/main.py
tronpyapi-0.0.1.dist-info/LICENSE.txt
tronpyapi-0.0.1.dist-info/METADATA
tronpyapi-0.0.1.dist-info/WHEEL
tronpyapi-0.0.1.dist-info/top_level.txt
tronpyapi-0.0.1.dist-info/RECORD
