Metadata-Version: 2.1
Name: tronpyapi
Version: 0.0.1
Summary: tronpyapi library for Python
Author: vikaron
Author-email: awake.meerkat.ploo@letterprotect.net
License: MIT
Project-URL: Source Repository, https://github.com
License-File: LICENSE.txt
Requires-Dist: requests
